{"_eventid": 2, "_event": "NNet.Game.SLoadingProgressMessage", "_bits": 56, "m_progress": 10, "_gameloop": 0, "_userid": {"m_userId": 2}}
{"_eventid": 2, "_event": "NNet.Game.SLoadingProgressMessage", "_bits": 56, "m_progress": 10, "_gameloop": 0, "_userid": {"m_userId": 3}}
{"_eventid": 2, "_event": "NNet.Game.SLoadingProgressMessage", "_bits": 56, "m_progress": 8, "_gameloop": 0, "_userid": {"m_userId": 7}}
{"_eventid": 2, "_event": "NNet.Game.SLoadingProgressMessage", "_bits": 56, "m_progress": 5, "_gameloop": 0, "_userid": {"m_userId": 8}}
{"_eventid": 2, "_event": "NNet.Game.SLoadingProgressMessage", "_bits": 56, "m_progress": 10, "_gameloop": 0, "_userid": {"m_userId": 4}}
{"_eventid": 2, "_event": "NNet.Game.SLoadingProgressMessage", "_bits": 56, "m_progress": 9, "_gameloop": 0, "_userid": {"m_userId": 9}}
{"_eventid": 2, "_event": "NNet.Game.SLoadingProgressMessage", "_bits": 56, "m_progress": 10, "_gameloop": 0, "_userid": {"m_userId": 6}}
{"_eventid": 2, "_event": "NNet.Game.SLoadingProgressMessage", "_bits": 56, "m_progress": 8, "_gameloop": 0, "_userid": {"m_userId": 5}}
{"_eventid": 2, "_event": "NNet.Game.SLoadingProgressMessage", "_bits": 56, "m_progress": 12, "_gameloop": 0, "_userid": {"m_userId": 8}}
{"_eventid": 2, "_event": "NNet.Game.SLoadingProgressMessage", "_bits": 56, "m_progress": 9, "_gameloop": 0, "_userid": {"m_userId": 0}}
{"_eventid": 2, "_event": "NNet.Game.SLoadingProgressMessage", "_bits": 56, "m_progress": 17, "_gameloop": 0, "_userid": {"m_userId": 2}}
{"_eventid": 2, "_event": "NNet.Game.SLoadingProgressMessage", "_bits": 56, "m_progress": 24, "_gameloop": 0, "_userid": {"m_userId": 2}}
{"_eventid": 2, "_event": "NNet.Game.SLoadingProgressMessage", "_bits": 56, "m_progress": 14, "_gameloop": 0, "_userid": {"m_userId": 0}}
{"_eventid": 2, "_event": "NNet.Game.SLoadingProgressMessage", "_bits": 56, "m_progress": 17, "_gameloop": 0, "_userid": {"m_userId": 3}}
{"_eventid": 2, "_event": "NNet.Game.SLoadingProgressMessage", "_bits": 56, "m_progress": 30, "_gameloop": 0, "_userid": {"m_userId": 2}}
{"_eventid": 2, "_event": "NNet.Game.SLoadingProgressMessage", "_bits": 56, "m_progress": 20, "_gameloop": 0, "_userid": {"m_userId": 0}}
{"_eventid": 2, "_event": "NNet.Game.SLoadingProgressMessage", "_bits": 56, "m_progress": 24, "_gameloop": 0, "_userid": {"m_userId": 3}}
{"_eventid": 2, "_event": "NNet.Game.SLoadingProgressMessage", "_bits": 56, "m_progress": 25, "_gameloop": 0, "_userid": {"m_userId": 0}}
{"_eventid": 2, "_event": "NNet.Game.SLoadingProgressMessage", "_bits": 56, "m_progress": 14, "_gameloop": 0, "_userid": {"m_userId": 9}}
{"_eventid": 2, "_event": "NNet.Game.SLoadingProgressMessage", "_bits": 56, "m_progress": 30, "_gameloop": 0, "_userid": {"m_userId": 0}}
{"_eventid": 2, "_event": "NNet.Game.SLoadingProgressMessage", "_bits": 56, "m_progress": 14, "_gameloop": 0, "_userid": {"m_userId": 7}}
{"_eventid": 2, "_event": "NNet.Game.SLoadingProgressMessage", "_bits": 56, "m_progress": 20, "_gameloop": 0, "_userid": {"m_userId": 9}}
{"_eventid": 2, "_event": "NNet.Game.SLoadingProgressMessage", "_bits": 56, "m_progress": 15, "_gameloop": 0, "_userid": {"m_userId": 6}}
{"_eventid": 2, "_event": "NNet.Game.SLoadingProgressMessage", "_bits": 56, "m_progress": 25, "_gameloop": 0, "_userid": {"m_userId": 9}}
{"_eventid": 2, "_event": "NNet.Game.SLoadingProgressMessage", "_bits": 56, "m_progress": 13, "_gameloop": 0, "_userid": {"m_userId": 5}}
{"_eventid": 2, "_event": "NNet.Game.SLoadingProgressMessage", "_bits": 56, "m_progress": 20, "_gameloop": 0, "_userid": {"m_userId": 6}}
{"_eventid": 2, "_event": "NNet.Game.SLoadingProgressMessage", "_bits": 56, "m_progress": 17, "_gameloop": 0, "_userid": {"m_userId": 8}}
{"_eventid": 2, "_event": "NNet.Game.SLoadingProgressMessage", "_bits": 56, "m_progress": 20, "_gameloop": 0, "_userid": {"m_userId": 7}}
{"_eventid": 2, "_event": "NNet.Game.SLoadingProgressMessage", "_bits": 56, "m_progress": 25, "_gameloop": 0, "_userid": {"m_userId": 6}}
{"_eventid": 2, "_event": "NNet.Game.SLoadingProgressMessage", "_bits": 56, "m_progress": 25, "_gameloop": 0, "_userid": {"m_userId": 7}}
{"_eventid": 2, "_event": "NNet.Game.SLoadingProgressMessage", "_bits": 56, "m_progress": 30, "_gameloop": 0, "_userid": {"m_userId": 3}}
{"_eventid": 2, "_event": "NNet.Game.SLoadingProgressMessage", "_bits": 56, "m_progress": 24, "_gameloop": 0, "_userid": {"m_userId": 8}}
{"_eventid": 2, "_event": "NNet.Game.SLoadingProgressMessage", "_bits": 56, "m_progress": 18, "_gameloop": 0, "_userid": {"m_userId": 5}}
{"_eventid": 2, "_event": "NNet.Game.SLoadingProgressMessage", "_bits": 56, "m_progress": 24, "_gameloop": 0, "_userid": {"m_userId": 5}}
{"_eventid": 2, "_event": "NNet.Game.SLoadingProgressMessage", "_bits": 56, "m_progress": 30, "_gameloop": 0, "_userid": {"m_userId": 6}}
{"_eventid": 2, "_event": "NNet.Game.SLoadingProgressMessage", "_bits": 56, "m_progress": 30, "_gameloop": 0, "_userid": {"m_userId": 7}}
{"_eventid": 2, "_event": "NNet.Game.SLoadingProgressMessage", "_bits": 56, "m_progress": 15, "_gameloop": 0, "_userid": {"m_userId": 4}}
{"_eventid": 2, "_event": "NNet.Game.SLoadingProgressMessage", "_bits": 56, "m_progress": 20, "_gameloop": 0, "_userid": {"m_userId": 4}}
{"_eventid": 2, "_event": "NNet.Game.SLoadingProgressMessage", "_bits": 56, "m_progress": 30, "_gameloop": 0, "_userid": {"m_userId": 8}}
{"_eventid": 2, "_event": "NNet.Game.SLoadingProgressMessage", "_bits": 56, "m_progress": 25, "_gameloop": 0, "_userid": {"m_userId": 4}}
{"_eventid": 2, "_event": "NNet.Game.SLoadingProgressMessage", "_bits": 56, "m_progress": 30, "_gameloop": 0, "_userid": {"m_userId": 9}}
{"_eventid": 2, "_event": "NNet.Game.SLoadingProgressMessage", "_bits": 56, "m_progress": 30, "_gameloop": 0, "_userid": {"m_userId": 5}}
{"_eventid": 2, "_event": "NNet.Game.SLoadingProgressMessage", "_bits": 56, "m_progress": 30, "_gameloop": 0, "_userid": {"m_userId": 4}}
{"_eventid": 2, "_event": "NNet.Game.SLoadingProgressMessage", "_bits": 56, "m_progress": 36, "_gameloop": 0, "_userid": {"m_userId": 8}}
{"_eventid": 2, "_event": "NNet.Game.SLoadingProgressMessage", "_bits": 56, "m_progress": 36, "_gameloop": 0, "_userid": {"m_userId": 7}}
{"_eventid": 2, "_event": "NNet.Game.SLoadingProgressMessage", "_bits": 56, "m_progress": 36, "_gameloop": 0, "_userid": {"m_userId": 3}}
{"_eventid": 2, "_event": "NNet.Game.SLoadingProgressMessage", "_bits": 56, "m_progress": 36, "_gameloop": 0, "_userid": {"m_userId": 5}}
{"_eventid": 2, "_event": "NNet.Game.SLoadingProgressMessage", "_bits": 56, "m_progress": 36, "_gameloop": 0, "_userid": {"m_userId": 4}}
{"_eventid": 2, "_event": "NNet.Game.SLoadingProgressMessage", "_bits": 56, "m_progress": 36, "_gameloop": 0, "_userid": {"m_userId": 0}}
{"_eventid": 2, "_event": "NNet.Game.SLoadingProgressMessage", "_bits": 56, "m_progress": 36, "_gameloop": 0, "_userid": {"m_userId": 6}}
{"_eventid": 2, "_event": "NNet.Game.SLoadingProgressMessage", "_bits": 56, "m_progress": 36, "_gameloop": 0, "_userid": {"m_userId": 2}}
{"_eventid": 2, "_event": "NNet.Game.SLoadingProgressMessage", "_bits": 56, "m_progress": 36, "_gameloop": 0, "_userid": {"m_userId": 9}}
{"_eventid": 2, "_event": "NNet.Game.SLoadingProgressMessage", "_bits": 56, "m_progress": 41, "_gameloop": 0, "_userid": {"m_userId": 8}}
{"_eventid": 2, "_event": "NNet.Game.SLoadingProgressMessage", "_bits": 56, "m_progress": 41, "_gameloop": 0, "_userid": {"m_userId": 3}}
{"_eventid": 2, "_event": "NNet.Game.SLoadingProgressMessage", "_bits": 56, "m_progress": 41, "_gameloop": 0, "_userid": {"m_userId": 5}}
{"_eventid": 2, "_event": "NNet.Game.SLoadingProgressMessage", "_bits": 56, "m_progress": 41, "_gameloop": 0, "_userid": {"m_userId": 6}}
{"_eventid": 2, "_event": "NNet.Game.SLoadingProgressMessage", "_bits": 56, "m_progress": 41, "_gameloop": 0, "_userid": {"m_userId": 9}}
{"_eventid": 2, "_event": "NNet.Game.SLoadingProgressMessage", "_bits": 56, "m_progress": 41, "_gameloop": 0, "_userid": {"m_userId": 4}}
{"_eventid": 2, "_event": "NNet.Game.SLoadingProgressMessage", "_bits": 56, "m_progress": 41, "_gameloop": 0, "_userid": {"m_userId": 0}}
{"_eventid": 2, "_event": "NNet.Game.SLoadingProgressMessage", "_bits": 56, "m_progress": 47, "_gameloop": 0, "_userid": {"m_userId": 7}}
{"_eventid": 2, "_event": "NNet.Game.SLoadingProgressMessage", "_bits": 56, "m_progress": 47, "_gameloop": 0, "_userid": {"m_userId": 2}}
{"_eventid": 2, "_event": "NNet.Game.SLoadingProgressMessage", "_bits": 56, "m_progress": 47, "_gameloop": 0, "_userid": {"m_userId": 8}}
{"_eventid": 2, "_event": "NNet.Game.SLoadingProgressMessage", "_bits": 56, "m_progress": 47, "_gameloop": 0, "_userid": {"m_userId": 6}}
{"_eventid": 2, "_event": "NNet.Game.SLoadingProgressMessage", "_bits": 56, "m_progress": 47, "_gameloop": 0, "_userid": {"m_userId": 3}}
{"_eventid": 2, "_event": "NNet.Game.SLoadingProgressMessage", "_bits": 56, "m_progress": 47, "_gameloop": 0, "_userid": {"m_userId": 5}}
{"_eventid": 2, "_event": "NNet.Game.SLoadingProgressMessage", "_bits": 56, "m_progress": 47, "_gameloop": 0, "_userid": {"m_userId": 9}}
{"_eventid": 2, "_event": "NNet.Game.SLoadingProgressMessage", "_bits": 56, "m_progress": 47, "_gameloop": 0, "_userid": {"m_userId": 0}}
{"_eventid": 2, "_event": "NNet.Game.SLoadingProgressMessage", "_bits": 56, "m_progress": 56, "_gameloop": 0, "_userid": {"m_userId": 7}}
{"_eventid": 2, "_event": "NNet.Game.SLoadingProgressMessage", "_bits": 56, "m_progress": 56, "_gameloop": 0, "_userid": {"m_userId": 8}}
{"_eventid": 2, "_event": "NNet.Game.SLoadingProgressMessage", "_bits": 56, "m_progress": 47, "_gameloop": 0, "_userid": {"m_userId": 4}}
{"_eventid": 2, "_event": "NNet.Game.SLoadingProgressMessage", "_bits": 56, "m_progress": 56, "_gameloop": 0, "_userid": {"m_userId": 9}}
{"_eventid": 2, "_event": "NNet.Game.SLoadingProgressMessage", "_bits": 56, "m_progress": 56, "_gameloop": 0, "_userid": {"m_userId": 5}}
{"_eventid": 2, "_event": "NNet.Game.SLoadingProgressMessage", "_bits": 56, "m_progress": 56, "_gameloop": 0, "_userid": {"m_userId": 3}}
{"_eventid": 2, "_event": "NNet.Game.SLoadingProgressMessage", "_bits": 56, "m_progress": 56, "_gameloop": 0, "_userid": {"m_userId": 6}}
{"_eventid": 2, "_event": "NNet.Game.SLoadingProgressMessage", "_bits": 56, "m_progress": 73, "_gameloop": 0, "_userid": {"m_userId": 8}}
{"_eventid": 2, "_event": "NNet.Game.SLoadingProgressMessage", "_bits": 56, "m_progress": 56, "_gameloop": 0, "_userid": {"m_userId": 2}}
{"_eventid": 2, "_event": "NNet.Game.SLoadingProgressMessage", "_bits": 56, "m_progress": 73, "_gameloop": 0, "_userid": {"m_userId": 2}}
{"_eventid": 2, "_event": "NNet.Game.SLoadingProgressMessage", "_bits": 56, "m_progress": 90, "_gameloop": 0, "_userid": {"m_userId": 7}}
{"_eventid": 2, "_event": "NNet.Game.SLoadingProgressMessage", "_bits": 56, "m_progress": 56, "_gameloop": 0, "_userid": {"m_userId": 4}}
{"_eventid": 2, "_event": "NNet.Game.SLoadingProgressMessage", "_bits": 56, "m_progress": 73, "_gameloop": 0, "_userid": {"m_userId": 5}}
{"_eventid": 2, "_event": "NNet.Game.SLoadingProgressMessage", "_bits": 56, "m_progress": 56, "_gameloop": 0, "_userid": {"m_userId": 0}}
{"_eventid": 2, "_event": "NNet.Game.SLoadingProgressMessage", "_bits": 56, "m_progress": 99, "_gameloop": 0, "_userid": {"m_userId": 7}}
{"_eventid": 2, "_event": "NNet.Game.SLoadingProgressMessage", "_bits": 56, "m_progress": 73, "_gameloop": 0, "_userid": {"m_userId": 3}}
{"_eventid": 2, "_event": "NNet.Game.SLoadingProgressMessage", "_bits": 56, "m_progress": 90, "_gameloop": 0, "_userid": {"m_userId": 2}}
{"_eventid": 2, "_event": "NNet.Game.SLoadingProgressMessage", "_bits": 56, "m_progress": 99, "_gameloop": 0, "_userid": {"m_userId": 2}}
{"_eventid": 2, "_event": "NNet.Game.SLoadingProgressMessage", "_bits": 56, "m_progress": 73, "_gameloop": 0, "_userid": {"m_userId": 9}}
{"_eventid": 2, "_event": "NNet.Game.SLoadingProgressMessage", "_bits": 56, "m_progress": 90, "_gameloop": 0, "_userid": {"m_userId": 8}}
{"_eventid": 2, "_event": "NNet.Game.SLoadingProgressMessage", "_bits": 56, "m_progress": 90, "_gameloop": 0, "_userid": {"m_userId": 9}}
{"_eventid": 2, "_event": "NNet.Game.SLoadingProgressMessage", "_bits": 56, "m_progress": 99, "_gameloop": 0, "_userid": {"m_userId": 9}}
{"_eventid": 2, "_event": "NNet.Game.SLoadingProgressMessage", "_bits": 56, "m_progress": 90, "_gameloop": 0, "_userid": {"m_userId": 3}}
{"_eventid": 2, "_event": "NNet.Game.SLoadingProgressMessage", "_bits": 56, "m_progress": 99, "_gameloop": 0, "_userid": {"m_userId": 8}}
{"_eventid": 2, "_event": "NNet.Game.SLoadingProgressMessage", "_bits": 56, "m_progress": 99, "_gameloop": 0, "_userid": {"m_userId": 3}}
{"_eventid": 2, "_event": "NNet.Game.SLoadingProgressMessage", "_bits": 56, "m_progress": 90, "_gameloop": 0, "_userid": {"m_userId": 5}}
{"_eventid": 2, "_event": "NNet.Game.SLoadingProgressMessage", "_bits": 56, "m_progress": 99, "_gameloop": 0, "_userid": {"m_userId": 5}}
{"_eventid": 2, "_event": "NNet.Game.SLoadingProgressMessage", "_bits": 56, "m_progress": 90, "_gameloop": 0, "_userid": {"m_userId": 6}}
{"_eventid": 2, "_event": "NNet.Game.SLoadingProgressMessage", "_bits": 56, "m_progress": 99, "_gameloop": 0, "_userid": {"m_userId": 6}}
{"_eventid": 2, "_event": "NNet.Game.SLoadingProgressMessage", "_bits": 56, "m_progress": 73, "_gameloop": 0, "_userid": {"m_userId": 4}}
{"_eventid": 2, "_event": "NNet.Game.SLoadingProgressMessage", "_bits": 56, "m_progress": 90, "_gameloop": 0, "_userid": {"m_userId": 4}}
{"_eventid": 2, "_event": "NNet.Game.SLoadingProgressMessage", "_bits": 56, "m_progress": 99, "_gameloop": 0, "_userid": {"m_userId": 4}}
{"_eventid": 2, "_event": "NNet.Game.SLoadingProgressMessage", "_bits": 56, "m_progress": 90, "_gameloop": 0, "_userid": {"m_userId": 0}}
{"_eventid": 2, "_event": "NNet.Game.SLoadingProgressMessage", "_bits": 56, "m_progress": 99, "_gameloop": 0, "_userid": {"m_userId": 0}}
{"m_recipient": 1, "_eventid": 1, "_event": "NNet.Game.SPingMessage", "_gameloop": 1045, "_bits": 96, "_userid": {"m_userId": 0}, "m_point": {"y": 671780, "x": 447860}}
{"m_recipient": 1, "_eventid": 1, "_event": "NNet.Game.SPingMessage", "_gameloop": 1061, "_bits": 88, "_userid": {"m_userId": 0}, "m_point": {"y": 691820, "x": 457995}}
{"m_recipient": 1, "_eventid": 1, "_event": "NNet.Game.SPingMessage", "_gameloop": 1095, "_bits": 88, "_userid": {"m_userId": 0}, "m_point": {"y": 699959, "x": 455743}}
{"_eventid": 4, "_event": "NNet.Game.SReconnectNotifyMessage", "_bits": 32, "_gameloop": 1205, "m_status": 2, "_userid": {"m_userId": 16}}
{"_eventid": 4, "_event": "NNet.Game.SReconnectNotifyMessage", "_bits": 24, "_gameloop": 1231, "m_status": 1, "_userid": {"m_userId": 16}}
{"_eventid": 2, "_event": "NNet.Game.SLoadingProgressMessage", "_bits": 56, "m_progress": 7, "_gameloop": 1280, "_userid": {"m_userId": 16}}
{"_eventid": 2, "_event": "NNet.Game.SLoadingProgressMessage", "_bits": 56, "m_progress": 12, "_gameloop": 1286, "_userid": {"m_userId": 16}}
{"_eventid": 2, "_event": "NNet.Game.SLoadingProgressMessage", "_bits": 64, "m_progress": 17, "_gameloop": 1503, "_userid": {"m_userId": 16}}
{"_eventid": 2, "_event": "NNet.Game.SLoadingProgressMessage", "_bits": 56, "m_progress": 24, "_gameloop": 1512, "_userid": {"m_userId": 16}}
{"_eventid": 2, "_event": "NNet.Game.SLoadingProgressMessage", "_bits": 64, "m_progress": 30, "_gameloop": 1588, "_userid": {"m_userId": 16}}
{"_eventid": 2, "_event": "NNet.Game.SLoadingProgressMessage", "_bits": 56, "m_progress": 37, "_gameloop": 1592, "_userid": {"m_userId": 16}}
{"_eventid": 2, "_event": "NNet.Game.SLoadingProgressMessage", "_bits": 56, "m_progress": 47, "_gameloop": 1602, "_userid": {"m_userId": 16}}
{"_eventid": 2, "_event": "NNet.Game.SLoadingProgressMessage", "_bits": 56, "m_progress": 56, "_gameloop": 1614, "_userid": {"m_userId": 16}}
{"_eventid": 2, "_event": "NNet.Game.SLoadingProgressMessage", "_bits": 56, "m_progress": 73, "_gameloop": 1633, "_userid": {"m_userId": 16}}
{"_eventid": 2, "_event": "NNet.Game.SLoadingProgressMessage", "_bits": 56, "m_progress": 90, "_gameloop": 1695, "_userid": {"m_userId": 16}}
{"_eventid": 2, "_event": "NNet.Game.SLoadingProgressMessage", "_bits": 56, "m_progress": 99, "_gameloop": 1699, "_userid": {"m_userId": 16}}
{"m_recipient": 1, "_eventid": 1, "_event": "NNet.Game.SPingMessage", "_gameloop": 2104, "_bits": 96, "_userid": {"m_userId": 0}, "m_point": {"y": 703919, "x": 507577}}
{"m_recipient": 1, "_eventid": 1, "_event": "NNet.Game.SPingMessage", "_gameloop": 2108, "_bits": 88, "_userid": {"m_userId": 0}, "m_point": {"y": 703256, "x": 509773}}
{"m_recipient": 1, "_eventid": 1, "_event": "NNet.Game.SPingMessage", "_gameloop": 2109, "_bits": 88, "_userid": {"m_userId": 0}, "m_point": {"y": 703253, "x": 509700}}
{"m_recipient": 1, "_eventid": 1, "_event": "NNet.Game.SPingMessage", "_gameloop": 6050, "_bits": 96, "_userid": {"m_userId": 1}, "m_point": {"y": 228050, "x": 539258}}
{"m_recipient": 1, "_eventid": 1, "_event": "NNet.Game.SPingMessage", "_gameloop": 10575, "_bits": 96, "_userid": {"m_userId": 1}, "m_point": {"y": 183705, "x": 410448}}
{"m_recipient": 1, "_eventid": 1, "_event": "NNet.Game.SPingMessage", "_gameloop": 24585, "_bits": 96, "_userid": {"m_userId": 2}, "m_point": {"y": 0, "x": 0}}
{"m_recipient": 1, "_eventid": 1, "_event": "NNet.Game.SPingMessage", "_gameloop": 24594, "_bits": 88, "_userid": {"m_userId": 1}, "m_point": {"y": 0, "x": 0}}
